MANIFEST.in
README.rst
setup.py
atlas_sdk/__init__.py
atlas_sdk/attribute_dict.py
atlas_sdk/channel.py
atlas_sdk/config.py
atlas_sdk/constants.py
atlas_sdk/request.py
atlas_sdk/runnable.py
atlas_sdk/skill.py
atlas_sdk/slot_data.py
atlas_sdk/topics.py
atlas_sdk/utils.py
atlas_sdk/version.py
atlas_sdk.egg-info/PKG-INFO
atlas_sdk.egg-info/SOURCES.txt
atlas_sdk.egg-info/dependency_links.txt
atlas_sdk.egg-info/requires.txt
atlas_sdk.egg-info/top_level.txt
atlas_sdk/adapters/__init__.py
atlas_sdk/adapters/adapter.py
atlas_sdk/adapters/channel_adapter.py
atlas_sdk/adapters/pubsub_adapter.py
atlas_sdk/adapters/skill_adapter.py
atlas_sdk/pubsubs/__init__.py
atlas_sdk/pubsubs/constants.py
atlas_sdk/pubsubs/handlers.py
atlas_sdk/pubsubs/mqtt_pubsub.py
atlas_sdk/pubsubs/pubsub.py