Metadata-Version: 1.0
Name: atlas-sdk
Version: 2.0.0
Summary: Python SDK to interact with atlas
Home-page: https://github.com/atlassistant/atlas-sdk
Author: Julien LEICHER
Author-email: UNKNOWN
License: GPL-3.0
Platform: UNKNOWN
